{
  "schemaVersion": 1,
  "manifest": {
    "name": "Fusion",
    "version": "1.3.0",
    "author": "Evolusion",
    "description": "Vibrant purple gradient with balanced glassmorphism.",
    "generatedAt": "2026-01-28T23:26:00.000Z"
  },
  "theme": {
    "id": "fusion",
    "name": "Fusion",
    "isCustom": false,
    "scheme": {
      "dark": {
        "dashboardBackgroundType": "gradient",
        "dashboardBackgroundColor1": "#4338ca",
        "dashboardBackgroundColor2": "#db2777",
        "dashboardGradientAngle": 135,
        "bgSidebar": "#000000",
        "sidebarOpacity": 0.2,
        "bgHeader": "#000000",
        "headerOpacity": 0.2,
        "bgChip": "rgba(255,255,255,0.1)",
        "bgCardHover": "rgba(255,255,255,0.05)",
        "bgDropdown": "#28283C",
        "bgInput": "rgba(255, 255, 255, 0.1)",
        "bgPanel": "rgba(0, 0, 0, 0.3)",
        "textPrimary": "#FFFFFF",
        "textSecondary": "rgba(255, 255, 255, 0.7)",
        "textMuted": "rgba(255, 255, 255, 0.5)",
        "borderInput": "rgba(255,255,255,0.1)",
        "borderFocus": "#ffffff",
        "borderDivider": "rgba(255,255,255,0.1)",
        "borderPrimary": "rgba(255,255,255,0.1)",
        "scrollbarThumb": "rgba(255,255,255,0.2)",
        "scrollbarTrack": "transparent",
        "cardOpacity": 0.4,
        "cardBorderRadius": 24,
        "cardBorderWidth": 1,
        "cardBorderColor": "rgba(255, 255, 255, 0.1)",
        "cardBorderColorOn": "rgba(255, 255, 255, 0.5)",
        "cardBackground": "rgba(40, 40, 60, 0.4)",
        "cardBackgroundOn": "rgba(50, 50, 70, 0.6)",
        "shadowCard": "0 8px 32px rgba(0, 0, 0, 0.2)",
        "panelOpacity": 0.3,
        "tabTextColor": "rgba(255, 255, 255, 0.6)",
        "activeTabTextColor": "#FFFFFF",
        "tabIndicatorColor": "#FFFFFF",
        "iconBackgroundShape": "circle",
        "iconBackgroundColorOn": "#FFFFFF",
        "iconBackgroundColorOff": "rgba(0, 0, 0, 0.2)",
        "iconColorOn": "#4338ca",
        "nameTextColor": "#FFFFFF",
        "statusTextColor": "rgba(255, 255, 255, 0.7)",
        "valueTextColor": "#FFFFFF",
        "unitTextColor": "rgba(255, 255, 255, 0.7)",
        "nameTextColorOn": "#FFFFFF",
        "statusTextColorOn": "#FFFFFF",
        "valueTextColorOn": "#FFFFFF",
        "unitTextColorOn": "#FFFFFF",
        "clockTextColor": "#FFFFFF",
        "weatherPrimaryColor": "#FFFFFF",
        "weatherSecondaryColor": "rgba(255, 255, 255, 0.7)",
        "thermostatHandleColor": "#FFFFFF",
        "thermostatDialTextColor": "#FFFFFF",
        "thermostatDialLabelColor": "rgba(255, 255, 255, 0.7)",
        "thermostatHeatingColor": "#FFFFFF",
        "thermostatCoolingColor": "#FFFFFF",
        "accentPrimary": "#FFFFFF",
        "accentError": "#FF453A",
        "accentSuccess": "#30D158",
        "accentWarning": "#FF9F0A",
        "accentInfo": "#FFFFFF",
        "widgetSwitchOn": "#30D158"
      },
      "light": {
        "dashboardBackgroundType": "gradient",
        "dashboardBackgroundColor1": "#E0E7FF",
        "dashboardBackgroundColor2": "#FAE8FF",
        "dashboardGradientAngle": 135,
        "bgSidebar": "#FFFFFF",
        "sidebarOpacity": 0.6,
        "bgHeader": "#FFFFFF",
        "headerOpacity": 0.6,
        "bgChip": "rgba(139, 92, 246, 0.1)",
        "bgCardHover": "rgba(0,0,0,0.03)",
        "bgDropdown": "#FFFFFF",
        "bgInput": "rgba(255, 255, 255, 0.5)",
        "bgPanel": "rgba(255, 255, 255, 0.6)",
        "textPrimary": "#374151",
        "textSecondary": "#6B7280",
        "textMuted": "#9CA3AF",
        "borderInput": "rgba(0,0,0,0.1)",
        "borderFocus": "#8B5CF6",
        "borderDivider": "rgba(0,0,0,0.05)",
        "borderPrimary": "rgba(139, 92, 246, 0.1)",
        "scrollbarThumb": "rgba(0,0,0,0.1)",
        "scrollbarTrack": "transparent",
        "cardOpacity": 0.5,
        "cardBorderRadius": 24,
        "cardBorderWidth": 0,
        "cardBorderColor": "transparent",
        "cardBorderColorOn": "#8B5CF6",
        "cardBackground": "#FFFFFF",
        "cardBackgroundOn": "#FFFFFF",
        "shadowCard": "0 4px 16px rgba(139, 92, 246, 0.1)",
        "panelOpacity": 0.6,
        "tabTextColor": "#6B7280",
        "activeTabTextColor": "#4F46E5",
        "tabIndicatorColor": "#4F46E5",
        "iconBackgroundShape": "circle",
        "iconBackgroundColorOn": "#8B5CF6",
        "iconBackgroundColorOff": "rgba(255, 255, 255, 0.5)",
        "iconColorOn": "#FFFFFF",
        "nameTextColor": "#374151",
        "statusTextColor": "#6B7280",
        "valueTextColor": "#4F46E5",
        "unitTextColor": "#6B7280",
        "nameTextColorOn": "#4338CA",
        "statusTextColorOn": "#8B5CF6",
        "valueTextColorOn": "#4F46E5",
        "unitTextColorOn": "#4F46E5",
        "clockTextColor": "#4F46E5",
        "weatherPrimaryColor": "#4F46E5",
        "weatherSecondaryColor": "#6B7280",
        "thermostatHandleColor": "#FFFFFF",
        "thermostatDialTextColor": "#4F46E5",
        "thermostatDialLabelColor": "#6B7280",
        "thermostatHeatingColor": "#8B5CF6",
        "thermostatCoolingColor": "#3B82F6",
        "accentPrimary": "#8B5CF6",
        "accentError": "#EF4444",
        "accentSuccess": "#34C759",
        "accentWarning": "#F59E0B",
        "accentInfo": "#3B82F6",
        "widgetSwitchOn": "#34C759"
      }
    }
  },
  "isBuiltIn": true
}